client/__init__.py
client/client.py
client/clientapp/__init__.py
client/clientapp/client_gui.py
client/clientapp/database_client.py
client/common/__init__.py
client/common/descriptrs.py
client/common/errors.py
client/common/metaclasses.py
client/common/utils.py
client/common/variables.py
client/doc/__init__.py
client/doc/source/__init__.py
client/doc/source/conf.py
client/logs/__init__.py
client/logs/client_log_config.py
client/logs/decor.py
client/logs/server_log_config.py
client/unit_tests/__init__.py
client/unit_tests/test_client.py
client/unit_tests/test_server.py
messenger_123_clients-0.0.4.dist-info/METADATA
messenger_123_clients-0.0.4.dist-info/WHEEL
messenger_123_clients-0.0.4.dist-info/top_level.txt
messenger_123_clients-0.0.4.dist-info/RECORD
